seu_injection/__init__.py
seu_injection/py.typed
seu_injection/version.py
seu_injection/bitops/__init__.py
seu_injection/bitops/float32.py
seu_injection/bitops/float32_legacy.py
seu_injection/bitops/utils.py
seu_injection/core/__init__.py
seu_injection/core/base_injector.py
seu_injection/core/exhaustive_seu_injector.py
seu_injection/core/stochastic_seu_injector.py
seu_injection/metrics/__init__.py
seu_injection/metrics/accuracy.py
seu_injection/utils/__init__.py
seu_injection/utils/device.py
seu_injection_framework-1.1.12.dist-info/METADATA
seu_injection_framework-1.1.12.dist-info/WHEEL
seu_injection_framework-1.1.12.dist-info/licenses/LICENSE
seu_injection_framework-1.1.12.dist-info/RECORD
