Metadata-Version: 2.4
Name: seu-injection-framework
Version: 1.1.12
Summary: Framework for Single Event Upset (SEU) injection in neural networks for harsh environment applications
Project-URL: Homepage, https://github.com/wd7512/seu-injection-framework
Project-URL: Documentation, https://github.com/wd7512/seu-injection-framework/blob/main/README.md
Project-URL: Repository, https://github.com/wd7512/seu-injection-framework
Project-URL: Bug Tracker, https://github.com/wd7512/seu-injection-framework/issues
Project-URL: Changelog, https://github.com/wd7512/seu-injection-framework/blob/main/CHANGELOG.md
Project-URL: Research Paper, https://research-information.bris.ac.uk/en/publications/a-framework-for-developing-robust-machine-learning-models-in-hars
Project-URL: Download, https://pypi.org/project/seu-injection-framework/
Author-email: William Dennis <wwdennis.home@gmail.com>
License: MIT
License-File: LICENSE
Keywords: fault-tolerance,machine-learning,neural-networks,radiation,robustness,seu
Classifier: Development Status :: 5 - Production/Stable
Classifier: Environment :: GPU :: NVIDIA CUDA
Classifier: Intended Audience :: Developers
Classifier: Intended Audience :: Science/Research
Classifier: License :: OSI Approved :: MIT License
Classifier: Natural Language :: English
Classifier: Operating System :: OS Independent
Classifier: Programming Language :: Python :: 3
Classifier: Programming Language :: Python :: 3 :: Only
Classifier: Programming Language :: Python :: 3.9
Classifier: Programming Language :: Python :: 3.10
Classifier: Programming Language :: Python :: 3.11
Classifier: Programming Language :: Python :: 3.12
Classifier: Topic :: Scientific/Engineering :: Artificial Intelligence
Classifier: Topic :: Scientific/Engineering :: Physics
Classifier: Topic :: Software Development :: Libraries :: Python Modules
Classifier: Topic :: Software Development :: Testing
Classifier: Typing :: Typed
Requires-Python: >=3.9
Requires-Dist: numpy<2.0.0,>=1.21.0
Requires-Dist: torch>=2.0.0
Requires-Dist: tqdm>=4.60.0
Provides-Extra: all
Requires-Dist: bandit>=1.7.0; extra == 'all'
Requires-Dist: ipywidgets>=7.0.0; extra == 'all'
Requires-Dist: joblib>=1.1.0; extra == 'all'
Requires-Dist: jupyter>=1.0.0; extra == 'all'
Requires-Dist: jupyterlab>=3.0.0; extra == 'all'
Requires-Dist: kagglehub>=0.1.0; extra == 'all'
Requires-Dist: matplotlib>=3.5.0; extra == 'all'
Requires-Dist: mdformat-gfm>=0.4.1; extra == 'all'
Requires-Dist: mdformat-toc>=0.5.0; extra == 'all'
Requires-Dist: mdformat>=0.7.22; extra == 'all'
Requires-Dist: mkdocs-material>=9.0.0; extra == 'all'
Requires-Dist: mkdocs>=1.5.0; extra == 'all'
Requires-Dist: mkdocstrings[python]>=0.24.0; extra == 'all'
Requires-Dist: pandas>=1.4.0; extra == 'all'
Requires-Dist: psutil>=7.1.3; extra == 'all'
Requires-Dist: pytest-cov>=4.0.0; extra == 'all'
Requires-Dist: pytest>=7.0.0; extra == 'all'
Requires-Dist: ruff>=0.1.0; extra == 'all'
Requires-Dist: scikit-image>=0.19.0; extra == 'all'
Requires-Dist: scikit-learn>=1.1.0; extra == 'all'
Requires-Dist: scipy>=1.8.0; extra == 'all'
Requires-Dist: seaborn>=0.11.0; extra == 'all'
Requires-Dist: statsmodels>=0.13.0; extra == 'all'
Requires-Dist: torchvision>=0.15.0; extra == 'all'
Requires-Dist: ty>=0.0.1a28; extra == 'all'
Provides-Extra: analysis
Requires-Dist: joblib>=1.1.0; extra == 'analysis'
Requires-Dist: matplotlib>=3.5.0; extra == 'analysis'
Requires-Dist: pandas>=1.4.0; extra == 'analysis'
Requires-Dist: scikit-image>=0.19.0; extra == 'analysis'
Requires-Dist: scikit-learn>=1.1.0; extra == 'analysis'
Requires-Dist: seaborn>=0.11.0; extra == 'analysis'
Requires-Dist: statsmodels>=0.13.0; extra == 'analysis'
Provides-Extra: dev
Requires-Dist: bandit>=1.7.0; extra == 'dev'
Requires-Dist: joblib>=1.1.0; extra == 'dev'
Requires-Dist: matplotlib>=3.5.0; extra == 'dev'
Requires-Dist: mdformat-gfm>=0.4.1; extra == 'dev'
Requires-Dist: mdformat-toc>=0.5.0; extra == 'dev'
Requires-Dist: mdformat>=0.7.22; extra == 'dev'
Requires-Dist: pandas>=1.4.0; extra == 'dev'
Requires-Dist: psutil>=7.1.3; extra == 'dev'
Requires-Dist: pytest-cov>=4.0.0; extra == 'dev'
Requires-Dist: pytest>=7.0.0; extra == 'dev'
Requires-Dist: ruff>=0.1.0; extra == 'dev'
Requires-Dist: scikit-image>=0.19.0; extra == 'dev'
Requires-Dist: scikit-learn>=1.1.0; extra == 'dev'
Requires-Dist: scipy>=1.8.0; extra == 'dev'
Requires-Dist: seaborn>=0.11.0; extra == 'dev'
Requires-Dist: statsmodels>=0.13.0; extra == 'dev'
Requires-Dist: torchvision>=0.15.0; extra == 'dev'
Requires-Dist: ty>=0.0.1a28; extra == 'dev'
Provides-Extra: docs
Requires-Dist: mkdocs-material>=9.0.0; extra == 'docs'
Requires-Dist: mkdocs>=1.5.0; extra == 'docs'
Requires-Dist: mkdocstrings[python]>=0.24.0; extra == 'docs'
Provides-Extra: examples
Requires-Dist: kagglehub>=0.1.0; extra == 'examples'
Provides-Extra: notebooks
Requires-Dist: ipywidgets>=7.0.0; extra == 'notebooks'
Requires-Dist: jupyter>=1.0.0; extra == 'notebooks'
Requires-Dist: jupyterlab>=3.0.0; extra == 'notebooks'
Provides-Extra: vision
Requires-Dist: torchvision>=0.15.0; extra == 'vision'
